announcer/__init__.py
announcer/changelogrenderer.py
announcer/teamschangelogrenderer.py
announcer-6.0.1.dist-info/LICENSE.md
announcer-6.0.1.dist-info/METADATA
announcer-6.0.1.dist-info/WHEEL
announcer-6.0.1.dist-info/entry_points.txt
announcer-6.0.1.dist-info/RECORD
