Metadata-Version: 2.3
Name: announcer
Version: 6.0.1
Summary: Announce changes in keepachangelog-style CHANGELOG.md files to Slack and Microsoft Teams
License: MIT
Keywords: slack,teams
Author: Max Dymond
Author-email: max.dymond@metaswitch.com
Requires-Python: >=3.9,<4.0.0
Classifier: License :: OSI Approved :: MIT License
Classifier: Programming Language :: Python :: 3
Classifier: Programming Language :: Python :: 3.9
Classifier: Programming Language :: Python :: 3.10
Classifier: Programming Language :: Python :: 3.11
Classifier: Programming Language :: Python :: 3.12
Classifier: Programming Language :: Python :: 3.13
Requires-Dist: mistletoe (>=1,<2)
Requires-Dist: requests (>=2.19,<3.0)
